main.py
splatpy/__init__.py
splatpy/api.py
splatpy/config.py
splatpy/incremental_pipeline.py
splatpy/trainer.py
splatpy/utils/colmap_datahandling.py
splatpy/utils/normalize.py
splatpy/utils/utils.py
splatpy-0.1.1.dist-info/licenses/LICENSE
splatpy-0.1.1.dist-info/METADATA
splatpy-0.1.1.dist-info/WHEEL
splatpy-0.1.1.dist-info/top_level.txt
splatpy-0.1.1.dist-info/RECORD
