Metadata-Version: 2.4
Name: splatpy
Version: 0.1.1
Summary: video to gaussian splat within minutes.
Author: cesipy
License: MIT
Requires-Python: >=3.10
License-File: LICENSE
Requires-Dist: gsplat>=1.5.0
Requires-Dist: pytorch-msssim>=1.0.0
Requires-Dist: imageio[ffmpeg]>=2.37.2
Requires-Dist: matplotlib>=3.10.8
Requires-Dist: numpy==1.26.4
Requires-Dist: opencv-python>=4.11.0.86
Requires-Dist: pycolmap>=3.13.0
Requires-Dist: scikit-learn>=1.7.2
Requires-Dist: torch>=2.6.0
Requires-Dist: torchvision>=0.21.0
Requires-Dist: tqdm>=4.67.1
Requires-Dist: setuptools
Requires-Dist: lpips
Provides-Extra: dev
Requires-Dist: pytest>=8.0.0; extra == "dev"
Requires-Dist: pytest-cov>=4.1.0; extra == "dev"
Requires-Dist: pytest-mock>=3.12.0; extra == "dev"
Requires-Dist: pytest-timeout>=2.2.0; extra == "dev"
Requires-Dist: pytest-xdist>=3.5.0; extra == "dev"
Dynamic: license-file
